drf_zettabyte/__init__.py
drf_zettabyte/models.py
drf_zettabyte/permissions.py
drf_zettabyte/serializers.py
drf_zettabyte/validations.py
drf_zettabyte/views.py
drf_zettabyte-0.0.1b0.dist-info/licenses/LICENSE
drf_zettabyte-0.0.1b0.dist-info/METADATA
drf_zettabyte-0.0.1b0.dist-info/WHEEL
drf_zettabyte-0.0.1b0.dist-info/top_level.txt
drf_zettabyte-0.0.1b0.dist-info/RECORD
